smsmobileapi_send_email/__init__.py
smsmobileapi_send_email/email_sender.py
smsmobileapi_send_email-0.3.3.dist-info/LICENSE
smsmobileapi_send_email-0.3.3.dist-info/METADATA
smsmobileapi_send_email-0.3.3.dist-info/WHEEL
smsmobileapi_send_email-0.3.3.dist-info/top_level.txt
smsmobileapi_send_email-0.3.3.dist-info/RECORD
