Metadata-Version: 2.2
Name: smsmobileapi-send-email
Version: 0.3.3
Summary: A Python module for sending emails using SMSMobileAPI directly from mailbox account
Home-page: https://github.com/SmsMobileApi/smsmobileapi-python-email
Author: Quest-Concept
Author-email: info@smsmobileapi.com
Classifier: Programming Language :: Python :: 3
Classifier: License :: OSI Approved :: MIT License
Classifier: Operating System :: OS Independent
Requires-Python: >=3.6
License-File: LICENSE
Requires-Dist: requests
Dynamic: author
Dynamic: author-email
Dynamic: classifier
Dynamic: description
Dynamic: description-content-type
Dynamic: home-page
Dynamic: requires-dist
Dynamic: requires-python
Dynamic: summary
